Mymodule_datecheck/__init__.py
Mymodule_datecheck-0.1.dist-info/METADATA
Mymodule_datecheck-0.1.dist-info/WHEEL
Mymodule_datecheck-0.1.dist-info/top_level.txt
Mymodule_datecheck-0.1.dist-info/RECORD
