Metadata-Version: 2.1
Name: Mymodule-datecheck
Version: 0.1
Summary: A module to check date format
Home-page: UNKNOWN
Author: Chintan
Author-email: chintan.suthar@xbyte.io
License: UNKNOWN
Platform: UNKNOWN
Classifier: Programming Language :: Python :: 3
Requires-Python: >=3.6
